README.md
setup.py
classarg/__init__.py
classarg.egg-info/PKG-INFO
classarg.egg-info/SOURCES.txt
classarg.egg-info/dependency_links.txt
classarg.egg-info/top_level.txt