Metadata-Version: 2.1
Name: classarg
Version: 0.0.2
Summary: A library for easily creating CLI applications.
Home-page: https://github.com/IanChen83/ClassArg
Author: Ian Chen
Author-email: patrickchen1994@gmail.com
License: UNKNOWN
Platform: UNKNOWN
Classifier: Development Status :: 1 - Planning
Classifier: Environment :: Console
Classifier: Intended Audience :: Developers
Classifier: License :: OSI Approved :: MIT License
Classifier: Operating System :: OS Independent
Classifier: Programming Language :: Python :: 3 :: Only
Classifier: Topic :: Software Development :: User Interfaces
Classifier: Topic :: Utilities
